covidstat/__init__.py
covidstat/rt.py
covidstat-0.0.1.dist-info/LICENSE
covidstat-0.0.1.dist-info/METADATA
covidstat-0.0.1.dist-info/WHEEL
covidstat-0.0.1.dist-info/top_level.txt
covidstat-0.0.1.dist-info/RECORD
